[
    {
        "title": "2019 Graduation",
        "date": "July, 2019",
        "credit": "Photo by St John's Communication Team",
        "linkToAuthor": "https://sjbdcs.org/author/communications-team",
        "src": "graduation.jpg",
        "alt": "Image couldn't load, please reload the page",
        "imgDir": "/images/",
        "widths": [320, 640, 1024],
        "sizes": "(min-width: 450px) 33.3vw, 100vw",
        "class": "gallery-photos",
        "width": 768,
        "height": 600
    },
    {
        "title": "Flag Day Celebration",
        "date": "2018",
        "credit": "Photo by St John's Communication Team",
        "linkToAuthor": "https://sjbdcs.org/author/communications-team",
        "src": "fd2.jpg",
        "alt": "Image couldn't load, please reload the page",
        "imgDir": "/images/",
        "widths": [320, 640, 1024],
        "sizes": "(min-width: 450px) 33.3vw, 100vw",
        "class": "gallery-photos",
        "width": 768,
        "height": 600
    },
    {
        "title": "Culture Day Celebrations",
        "date": "October 18, 2020",
        "credit": "Photo by St John's Communication Team",
        "linkToAuthor": "https://sjbdcs.org/author/communications-team",
        "src": "f2.jpg",
        "alt": "Image couldn't load, please reload the page",
        "imgDir": "/images/",
        "widths": [320, 640, 1024],
        "sizes": "(min-width: 450px) 33.3vw, 100vw",
        "class": "gallery-photos",
        "width": 768,
        "height": 600
    },
    {
        "title": "Sport Festival",
        "date": "October 16, 2020",
        "credit": "Photo by St John's Communication Team",
        "linkToAuthor": "https://sjbdcs.org/author/communications-team",
        "src": "sp.jpg",
        "alt": "Image couldn't load, please reload the page",
        "imgDir": "/images/",
        "widths": [320, 640, 1024],
        "sizes": "(min-width: 450px) 33.3vw, 100vw",
        "class": "gallery-photos",
        "width": 768,
        "height": 600
    },
    {
        "title": "Celebrating Teachers Day",
        "date": "October 14, 2020",
        "credit": "Photo by St John's Communication Team",
        "linkToAuthor": "https://sjbdcs.org/author/communications-team",
        "src": "f1.jpg",
        "alt": "Image couldn't load, please reload the page",
        "imgDir": "/images/",
        "widths": [320, 640, 1024],
        "sizes": "(min-width: 450px) 33.3vw, 100vw",
        "class": "gallery-photos",
        "width": 768,
        "height": 600
    },
    {
        "title": "Award Ceremony in the presence of his holiness",
        "date": "October 12, 2020",
        "credit": "Photo by St John's Communication Team",
        "linkToAuthor": "https://sjbdcs.org/author/communications-team",
        "src": "e1.jpg",
        "alt": "Image couldn't load, please reload the page",
        "imgDir": "/images/",
        "widths": [320, 640, 1024],
        "sizes": "(min-width: 450px) 33.3vw, 100vw",
        "class": "gallery-photos",
        "width": 768,
        "height": 600
    },
    {
        "title": "Students in class",
        "date": "October 10, 2020",
        "credit": "Photo by St John's Communication Team",
        "linkToAuthor": "https://sjbdcs.org/author/communications-team",
        "src": "class.jpg",
        "alt": "Image couldn't load, please reload the page",
        "imgDir": "/images/",
        "widths": [320, 640, 1024],
        "sizes": "(min-width: 450px) 33.3vw, 100vw",
        "class": "gallery-photos",
        "width": 768,
        "height": 600
    },
    {
        "title": "The School Choir",
        "date": "October 9, 2020",
        "credit": "Photo by St John's Communication Team",
        "linkToAuthor": "https://sjbdcs.org/author/communications-team",
        "src": "c4.jpg",
        "alt": "Image couldn't load, please reload the page",
        "imgDir": "/images/",
        "widths": [320, 640, 1024],
        "sizes": "(min-width: 450px) 33.3vw, 100vw",
        "class": "gallery-photos",
        "width": 768,
        "height": 600
    },
    {
        "title": "The Holy Liturgy",
        "date": "October 11, 2020",
        "credit": "Photo by St John's Communication Team",
        "linkToAuthor": "https://sjbdcs.org/author/communications-team",
        "src": "d4.jpg",
        "alt": "Image couldn't load, please reload the page",
        "imgDir": "/images/",
        "widths": [320, 640, 1024],
        "sizes": "(min-width: 450px) 33.3vw, 100vw",
        "class": "gallery-photos",
        "width": 768,
        "height": 600
    }
]
